talkweb/__init__.py
talkweb/cell.py
talkweb/cparser.py
talkweb/htmltocell.py
talkweb/wparser.py
talkweb-1.3.dist-info/METADATA
talkweb-1.3.dist-info/WHEEL
talkweb-1.3.dist-info/top_level.txt
talkweb-1.3.dist-info/RECORD
